mia/__init__.py
mia/__main__.py
mia/main.py
mia/archiver/__init__.py
mia/archiver/database.py
mia/archiver/storage.py
mia/archiver/web.py
mia/archiver/migrations/M001_initial.py
mia/archiver/migrations/__init__.py
mia/archiver/migrations/migration.py
mia/cli/__init__.py
mia/cli/archive.py
mia/util/__init__.py
mia/web/__init__.py
mia/web/app_keys.py
mia/web/archive.py
mia/web/middlewares.py
mia/web/server.py
miarchive-0.0.3.dist-info/licenses/LICENSE
miarchive-0.0.3.dist-info/METADATA
miarchive-0.0.3.dist-info/WHEEL
miarchive-0.0.3.dist-info/entry_points.txt
miarchive-0.0.3.dist-info/top_level.txt
miarchive-0.0.3.dist-info/RECORD
