Metadata-Version: 2.4
Name: miarchive
Version: 0.0.3
Summary: Self-hosted internet archive
Author-email: LunarWatcher <oliviawolfie@pm.me>
License-Expression: MIT
Project-URL: Homepage, https://codeberg.org/LunarWatcher/MIArchive
Project-URL: Documentation, https://codeberg.org/LunarWatcher/MIArchive
Project-URL: Repository, https://codeberg.org/LunarWatcher/MIArchive.git
Project-URL: Issues, https://codeberg.org/LunarWatcher/MIArchive/issues
Project-URL: Changelog, https://github.com/LunarWatcher/MIArchive/releases
Keywords: archival,web archiving,internet archiving,web,browser,download,preservation
Classifier: Development Status :: 4 - Beta
Classifier: Environment :: Console
Classifier: Topic :: System :: Archiving
Classifier: Topic :: Utilities
Classifier: Framework :: aiohttp
Classifier: Intended Audience :: Developers
Classifier: Intended Audience :: Education
Classifier: Intended Audience :: End Users/Desktop
Classifier: Intended Audience :: System Administrators
Classifier: Programming Language :: Python :: 3
Classifier: Programming Language :: Python :: 3.10
Classifier: Programming Language :: Python :: 3.11
Classifier: Programming Language :: Python :: 3.12
Classifier: Programming Language :: Python :: 3.13
Classifier: Operating System :: POSIX :: Linux
Requires-Python: >=3.10
License-File: LICENSE
Requires-Dist: undetected-geckodriver-lw
Requires-Dist: selenium-wire-lw[uf]
Requires-Dist: beautifulsoup4==4.13.3
Requires-Dist: psycopg==3.2.9
Requires-Dist: aiohttp==3.12.13
Requires-Dist: aiohttp-jinja2==1.6
Requires-Dist: aiohttp_cors==0.8.1
Requires-Dist: msgspec>=0.19.0
Requires-Dist: loguru>=0.7.3
Requires-Dist: requests
Dynamic: license-file
